odoo9_addon_packaging_uom-9.0.1.0.0.99.dev3-nspkg.pth
odoo_addons/packaging_uom/README.rst
odoo_addons/packaging_uom/__init__.py
odoo_addons/packaging_uom/__openerp__.py
odoo_addons/packaging_uom/i18n/cs_CZ.po
odoo_addons/packaging_uom/i18n/de.po
odoo_addons/packaging_uom/i18n/es.po
odoo_addons/packaging_uom/i18n/fi.po
odoo_addons/packaging_uom/i18n/fr.po
odoo_addons/packaging_uom/i18n/hr.po
odoo_addons/packaging_uom/i18n/hr_HR.po
odoo_addons/packaging_uom/i18n/it.po
odoo_addons/packaging_uom/i18n/nl.po
odoo_addons/packaging_uom/i18n/packaging_uom.pot
odoo_addons/packaging_uom/i18n/pt.po
odoo_addons/packaging_uom/i18n/pt_BR.po
odoo_addons/packaging_uom/i18n/sl.po
odoo_addons/packaging_uom/models/__init__.py
odoo_addons/packaging_uom/models/product_packaging.py
odoo_addons/packaging_uom/readme/CONFIGURE.rst
odoo_addons/packaging_uom/readme/CONTRIBUTORS.rst
odoo_addons/packaging_uom/readme/DESCRIPTION.rst
odoo_addons/packaging_uom/readme/INSTALLATION.rst
odoo_addons/packaging_uom/static/description/icon.png
odoo_addons/packaging_uom/static/description/index.html
odoo_addons/packaging_uom/tests/__init__.py
odoo_addons/packaging_uom/tests/test_product_packaging.py
odoo_addons/packaging_uom/views/product_packaging_views.xml
odoo9_addon_packaging_uom-9.0.1.0.0.99.dev3.dist-info/METADATA
odoo9_addon_packaging_uom-9.0.1.0.0.99.dev3.dist-info/WHEEL
odoo9_addon_packaging_uom-9.0.1.0.0.99.dev3.dist-info/namespace_packages.txt
odoo9_addon_packaging_uom-9.0.1.0.0.99.dev3.dist-info/top_level.txt
odoo9_addon_packaging_uom-9.0.1.0.0.99.dev3.dist-info/RECORD
